balder/.vscode/settings.json
balder/__init__.py
balder/apps.py
balder/autodiscover.py
balder/consumers.py
balder/enum.py
balder/fields/__init__.py
balder/fields/filtered.py
balder/fields/offsetfiltered.py
balder/filters/__init__.py
balder/filters/enum.py
balder/filters/multi_enum.py
balder/registry.py
balder/scalars.py
balder/schema.py
balder/templates/balder/graphiql-ws.html
balder/templates/balder/graphiql.html
balder/types/__init__.py
balder/types/mutation/__init__.py
balder/types/mutation/base.py
balder/types/mutation/meta.py
balder/types/object.py
balder/types/query/__init__.py
balder/types/query/base.py
balder/types/query/meta.py
balder/types/scalars.py
balder/types/subscription/__init__.py
balder/types/subscription/base.py
balder/types/subscription/meta.py
balder/types/subscription/serializer.py
balder/types/utils.py
balder/urls.py
balder/views.py
balder-0.1.30.dist-info/METADATA
balder-0.1.30.dist-info/WHEEL
balder-0.1.30.dist-info/RECORD
