Metadata-Version: 2.1
Name: balder
Version: 0.1.30
Summary: 
Author: jhnnsrs
Author-email: jhnnsrs@gmail.com
Requires-Python: >=3.8,<4.0
Classifier: Programming Language :: Python :: 3
Classifier: Programming Language :: Python :: 3.8
Classifier: Programming Language :: Python :: 3.9
Classifier: Programming Language :: Python :: 3.10
Classifier: Programming Language :: Python :: 3.11
Provides-Extra: subscription
Requires-Dist: Django (==3.2.19)
Requires-Dist: channels (==3.0.5) ; extra == "subscription"
Requires-Dist: django-channels-graphql-ws (==0.8.0) ; extra == "subscription"
Requires-Dist: django-filter (==2.4.0)
Requires-Dist: graphene (==2.1.9)
Requires-Dist: graphene-django (==2.14.0)
Requires-Dist: graphene-file-upload (==1.3.0)
